intersystems_pyprod/__init__.py
intersystems_pyprod/_method_stubs.py
intersystems_pyprod/_parser.py
intersystems_pyprod/_production_connector.py
intersystems_pyprod/py.typed
intersystems_pyprod-0.1.0.dist-info/METADATA
intersystems_pyprod-0.1.0.dist-info/WHEEL
intersystems_pyprod-0.1.0.dist-info/entry_points.txt
intersystems_pyprod-0.1.0.dist-info/top_level.txt
intersystems_pyprod-0.1.0.dist-info/RECORD
