Metadata-Version: 2.4
Name: intersystems-pyprod
Version: 0.1.0
Summary: Pure Python Interoperability Productions using InterSystems IRIS
Author-email: Geet Kalra <geet.kalra@intersystems.com>
License-Expression: MIT
Project-URL: Homepage, https://github.com/intersystems/pyprod
Project-URL: Source, https://github.com/intersystems/pyprod
Project-URL: Issues, https://github.com/intersystems/pyprod/issues
Project-URL: Documentation, https://github.com/intersystems/pyprod#readme
Classifier: Programming Language :: Python :: 3
Classifier: Programming Language :: Python :: 3.9
Classifier: Programming Language :: Python :: 3.10
Classifier: Programming Language :: Python :: 3.11
Classifier: Programming Language :: Python :: 3.12
Classifier: Intended Audience :: Developers
Requires-Python: >=3.9
